pyignite/__init__.py
pyignite/_cutils.cp37-win_amd64.pyd
pyignite/aio_cache.py
pyignite/aio_client.py
pyignite/aio_cluster.py
pyignite/binary.py
pyignite/cache.py
pyignite/client.py
pyignite/cluster.py
pyignite/constants.py
pyignite/cursors.py
pyignite/exceptions.py
pyignite/monitoring.py
pyignite/transaction.py
pyignite/utils.py
pyignite/api/__init__.py
pyignite/api/affinity.py
pyignite/api/binary.py
pyignite/api/cache_config.py
pyignite/api/cluster.py
pyignite/api/key_value.py
pyignite/api/result.py
pyignite/api/sql.py
pyignite/api/tx_api.py
pyignite/connection/__init__.py
pyignite/connection/aio_connection.py
pyignite/connection/bitmask_feature.py
pyignite/connection/connection.py
pyignite/connection/handshake.py
pyignite/connection/protocol_context.py
pyignite/connection/ssl.py
pyignite/datatypes/__init__.py
pyignite/datatypes/base.py
pyignite/datatypes/binary.py
pyignite/datatypes/cache_config.py
pyignite/datatypes/cache_properties.py
pyignite/datatypes/cluster_state.py
pyignite/datatypes/complex.py
pyignite/datatypes/expiry_policy.py
pyignite/datatypes/internal.py
pyignite/datatypes/key_value.py
pyignite/datatypes/null_object.py
pyignite/datatypes/primitive.py
pyignite/datatypes/primitive_arrays.py
pyignite/datatypes/primitive_objects.py
pyignite/datatypes/prop_codes.py
pyignite/datatypes/sql.py
pyignite/datatypes/standard.py
pyignite/datatypes/transactions.py
pyignite/datatypes/type_codes.py
pyignite/datatypes/type_ids.py
pyignite/datatypes/type_names.py
pyignite/queries/__init__.py
pyignite/queries/cache_info.py
pyignite/queries/op_codes.py
pyignite/queries/query.py
pyignite/queries/response.py
pyignite/stream/__init__.py
pyignite/stream/binary_stream.py
pyignite-0.6.1.dist-info/LICENSE
pyignite-0.6.1.dist-info/METADATA
pyignite-0.6.1.dist-info/NOTICE
pyignite-0.6.1.dist-info/WHEEL
pyignite-0.6.1.dist-info/top_level.txt
pyignite-0.6.1.dist-info/RECORD
