Metadata-Version: 2.1
Name: pyignite
Version: 0.6.1
Summary: Apache Ignite binary client Python API
Home-page: https://github.com/apache/ignite-python-thin-client
Author: The Apache Software Foundation
Author-email: dev@ignite.apache.org
License: Apache License 2.0
Classifier: Programming Language :: Python
Classifier: Programming Language :: Python :: 3
Classifier: Programming Language :: Python :: 3.7
Classifier: Programming Language :: Python :: 3.8
Classifier: Programming Language :: Python :: 3.9
Classifier: Programming Language :: Python :: 3.10
Classifier: Programming Language :: Python :: 3.11
Classifier: Programming Language :: Python :: 3 :: Only
Classifier: Intended Audience :: Developers
Classifier: Topic :: Database :: Front-Ends
Classifier: Topic :: Software Development :: Libraries :: Python Modules
Classifier: License :: OSI Approved :: Apache Software License
Classifier: Operating System :: OS Independent
Requires-Python: >=3.7
License-File: LICENSE
License-File: NOTICE
Requires-Dist: attrs (>=20.3.0)
